{
  "name": "Hilda Wallace",
  "age": 65,
  "address": {
    "street": "Jodmab Square",
    "city": "Izifoaku",
    "state": "WA",
    "zip": "70966"
  },
  "contact": {
    "phone": "(665) 392-6323",
    "servicePhone": "800947723"
  },
  "birthday": "1984-09-15T17:45:04.471Z",
  "ip": "93.13.119.24",
  "foo": "bar",
  "profile": {
    "about": "Hulled haurmud gef ed za iracobja josja vicnip tavvohde nezsugav gitow igruksak. Foc tocit puw gibve nuvlaloj ikpog wa wutuwot vuw hiputri res paodima apamovwim igi viej faheibe tamijhi. Pokih umjo dodosto beffunci mibcocduh ralic rijouv ro uwoin votazo latakrez evle. Wodma hek ce no hoikewud nu dakpo sag vez voma raji mu beoca wetsupkin. Ci siniczuw cotjo du celowmur di ezeabefo nije izubit fok jojhuwuj seri tadose hutjufi. Dice ufraj ar amjihi lew rezohniw jesafas caj hoslojzoz ewfit ret ledmacuf sibelu. Iha watmazgo gi fehurhu tel kocjotoz ho voccujgon cur ufazowje ijaud mazokbaz li.",
    "bio": "Pit zic zap masar wufagodu wiacvov opidew kuli pawaviki baksepir fedter likne cisulow epese jiwowaba sesa. Vifamsov wi pewjuv baf jouw hitlo wa ocizu repve rutohu tiepa vafsedip si soj henji ozuhin vi. Esiuncef radig uva jizahuog lij luhcehbi ifti lepsi opwepi sejnavi mijzuaj vohehvo lebumrem fowhiga zites cun ahooh tuzraere. Nuzuzuv ra sos gikufu odomufso zasfev cirdit poru cobej dicunko ok vijaweeca kivvip minebvaj nicjaw iwoctow cuov."
  },
  "apiKey": "ca4787fd2ae68ff592301ced3c74239cf19527e975e8f01a4977a7e5c30b6ca0",
  "currency": {
    "code": "RON",
    "name": "Romania New Leu"
  }
}