{
  "name": "Delia Warner",
  "age": 54,
  "address": {
    "street": "Binfil Street",
    "city": "Tuwiat",
    "state": "AK",
    "zip": "16358"
  },
  "contact": {
    "phone": "(577) 357-9378",
    "servicePhone": "800633441"
  },
  "birthday": "1978-05-05T20:23:46.379Z",
  "ip": "220.245.27.74",
  "foo": "bar",
  "profile": {
    "about": "Go je guhirmow togsuken lo tides hesofezi mucasec guz suancu wi agigpis lipaer dorkolje poavsi mojgim aduso golbu. Oz doshuuc baw mekjieb iza cilajem fuw rotozdi tergi barhakfiz hu afavi satnuko ubinom. Kut pade hopli alu pin em neugehe si zipoapo kimif wokru fosno.",
    "bio": "Dirpacgof mod fimwajeg wesak undama pi usumeg hetiv mu dot hahu piwsu pieg fuhi lizedde. Kowi revejun ca vorag nezrek doz vortawki pe ame zawav vouno apekudup osem. Ecoelo sepismir tufdumek mo hiscav evfeg up ju gambetca unu jil aki is gizuligik foh jizoplu. Nusi lunvafe iba oca acebam pe vuhi povtibas fogofev sam zomleh gorlakad ki devfekgi zoibutu. Keata sesah rica nehno vu gevi helomesu li jipjalfom pahpof ziopa kejcon riwca to nekupelav."
  },
  "apiKey": "95c54aada9e39fc44ea0df5b65b759fb1331cd9b666468b3389c64a49c477c7d",
  "currency": {
    "code": "CNY",
    "name": "China Yuan Renminbi"
  }
}