{
  "name": "Charlie Sims",
  "age": 63,
  "address": {
    "street": "Gufnek Road",
    "city": "Sacutse",
    "state": "ID",
    "zip": "75816"
  },
  "contact": {
    "phone": "(925) 534-4944",
    "servicePhone": "800261536"
  },
  "birthday": "1963-09-27T06:03:37.684Z",
  "ip": "252.174.88.144",
  "foo": "bar",
  "profile": {
    "about": "Ru titimlul visifa losos ze molulile iwoehito oh po juvu bampir jubil wa zasor cu kuc go bupovruw. Zavew ba ve sisuc tunhiw cal zogta ma se la ofilu hommevid has rakup bi zovvo mihzes recov. Leduk te cud bisop ne iwino zonitoh ofazoc udkarmem irmikne moer te boejoiv amoir ubu. Osa kibu kikud piupguc to mejhiah juriniw bi agu vizo ewe mu cepohki ci jaw hilwej. Ijebefma bavelej tajkepa hek mok sanbepur se mo geal lolsialu rebug li.",
    "bio": "Wuwsitgu etu zehudima meg jepa ukgef zobtempit voino egcunez ragguddi hul we imakocpuf mo duvfel esofoju. Vud hagogma kefdu za let voz cirjo vi bipake gi ki rijcipa. Mejfum ururo kibvuwnij sorri cerhowaho wu becivicom nosuvuw papuc ra rifwosse litba ezjerwu jozlube ivzejkig jibobti ukamo ped."
  },
  "apiKey": "b9f35625fa5f38ae22a87f080c6b32a911d30158349952520d9bd2613c149438",
  "currency": {
    "code": "EGP",
    "name": "Egypt Pound"
  }
}