{
  "name": "Luis Greer",
  "age": 62,
  "address": {
    "street": "Igwoz Park",
    "city": "Sawuve",
    "state": "AZ",
    "zip": "29177"
  },
  "contact": {
    "phone": "(803) 574-7970",
    "servicePhone": "800168579"
  },
  "birthday": "1986-03-31T10:36:11.653Z",
  "ip": "144.63.218.205",
  "foo": "bar",
  "profile": {
    "about": "Ziwdog wauhudeh tithe ib zapal ba jez kup dazor ukida deknad neh kewa orbi ca gipkun visicaes arzef. Ojlehid zerilfa vijaczer fekaz gackouj taj ebupetar bubmine pi ozodison hubhi athas. Ka ub ni paevule cucrivbow heh mocir lu aj worceg vil uselu urkozgi icecec uvwulme uve biepu. Wegeku pibarzis fuhocgo gegled hakde ujouv etajovu luzcevvi livho ihauz gadam nivmaje.",
    "bio": "Gezasi olozris gonica bidja nugopuca pogsu fugihwa og ovzo fuj kegico ikotugo. Gum javev pibip tonuh ah vunfoz zo kuf uviwsa je vunako izo ze pojud ihikim. Peztitol awuivtof inwis jum saif howuko zuama losormek jun tafnako wuwukeve ko budan cigeti jorpag ed. Nezpieki gidovin cu hu huunwum nepah oh getar cozik ipu ocmidlir co gadromato modapde pu ris iju lus. Nakke itbut opfe jumem vatef wad kuzfois zinedi eh cabuh ulwugeje usi lehibaked cigri we uzpi dazak iha."
  },
  "apiKey": "e0bee0a30ff82e64108abdbc1b3efcac54418103ab06538bf1d4ae6923f194d1",
  "currency": {
    "code": "IQD",
    "name": "Iraq Dinar"
  }
}