{
  "name": "Todd Roberson",
  "age": 29,
  "address": {
    "street": "Ufiuhe Drive",
    "city": "Wetvahof",
    "state": "WY",
    "zip": "08760"
  },
  "contact": {
    "phone": "(686) 945-7638",
    "servicePhone": "800275153"
  },
  "birthday": "1977-06-10T12:44:58.459Z",
  "ip": "231.62.40.202",
  "foo": "bar",
  "profile": {
    "about": "Rijvu rejvutvi ucgi adu noverha hol vuicabok rumaiz raztil fepis mucfu zowi pavmuzan. Jac do fuic zuvmawliv mem pejazoz lugmiwoz waw ipistif eb gisu geeva lubap kow. Eri vejrodo benreb zow gutekwa luazepi sic bezbokwe nazwi maf lirak tu zicsanef opcinro zeefi. Zen din dirnusi ehrecul jipaw ko lakiga evouwu os etmo ecefij pekin ru jozifus dianaja vesalib dov. Wus suziru zaheepe zog id cuaseje uhlik wizet lifa tuhrani detzim sasu urama nupe jic iptoljon kuf ewrupvuk. Gemguwi ji tot da sutwatjej hanpuwuh op ukawiwi putti pi ez ucwocon guzah ej godepo haco.",
    "bio": "Neg lovawur funve egeiwa buwew taji pi uco efeso sogra hih licahiive id. He agu bandaf jawuzdet ajiliniv epusi soed jisejwil alnenaj kan pubci os igcot uzewiz bol. Gilop hi bed suvpuj owi tocutcet mug hi ge hat basaja alve fuganad fere pujiahe diftic. Nuru kokfiuw vouhpi ac cac awole uri nuniv zadwires if pufpoj ri to te kuksugap ow. Imoow kic nawhemude ibud uga jaihi powuthu vu pilbo hirolmis mukpepmor hef nacki zumibuw eru nahbi kazu hohug. At tafid wa hocuj ekpiuto da jubepca nazza wi vaola caov lowfom miaphuh asuot tuhbaz. Mav jojov loruh ahcefehe wu mo epdikig lono ucanan luben poz ivi dakegah dojanlom gul vo hewojhe."
  },
  "apiKey": "c8777de2eff26c435a974ee13175d3054db626c21d7b8108beb824306cfce3f5",
  "currency": {
    "code": "DJF",
    "name": "Djibouti Franc"
  }
}