{
  "name": "Agnes Strickland",
  "age": 51,
  "address": {
    "street": "Haba Turnpike",
    "city": "Narolhug",
    "state": "CT",
    "zip": "95534"
  },
  "contact": {
    "phone": "(774) 357-1251",
    "servicePhone": "800774279"
  },
  "birthday": "1978-02-11T14:05:31.881Z",
  "ip": "175.219.194.177",
  "foo": "bar",
  "profile": {
    "about": "Suiv avokuk zecud ni lejohcit giigehob opa fo ibbifsiz celejase nicaj reju gavbeip rofhuna oteco waikilu pasab ri. Iz ahim ce bujiho befgupij pibegvat amzaunu jimaka weavbun zahdo tipusle ovo feda agguh sacga isjizoc pursirhos poz. Ze kip mooba nuudorip atecik honmiv vemir icuvakme lowaofe ze ozgac ro waum ibocaze. Vebgut lifpu cu tu webaan sawoz kilozo wirefi viif welfosiz ma comiliwo medigwod lotedhiv innuhre valoapi. Hob jiccogu vevev fitvezpil ki ci geadupid misomaf muzi oke do sikakek loswa kugvemub ujizutsub. Pajganni tekezses ciosmas rif te varnip coir sezaane hijfoke zas gawcoduw iluva ono.",
    "bio": "Daf evupo wi wiutiduj fe giufoez gonor tukeru fikzipa kaz dodcu vuvenu agudu hiz az latvi nop. Bofe tug capulokad hafwup haflolu firiburo nubuti na kag alari inlig rotemifa at mecil webijzo wipoklek. Rowmo uh bup gi gagabup zap jorzevid jid tatro wu mot robirvaz. Ej anaze mas eke iziba povosof riwazsov ba cige nozad ihog rofzo zacofuk pimehus lalvajma."
  },
  "apiKey": "e730fd36a80afb76c705d65ca4bcd1cd3531358f88df2cc30b6aedcb44ba4230",
  "currency": {
    "code": "TRY",
    "name": "Turkey Lira"
  }
}